
{
    "Mountain Lion": {
        "name": "Mountain Lion",
        "health": 150,
        "weapon": "Claws"
    },
    "Spider": {
        "name": "Spider",
        "health": 15,
        "weapon": "Poison Fangs"
    },
    "Goblin": {
        "name": "Goblin",
        "health": 30,
        "weapon": "Club"
    },
    "Wolf": {
        "name": "Wolf",
        "health": 50,
        "weapon": "Bite"
    },
    "Vampire Bat": {
        "name": "Vampire Bat",
        "health": 30,
        "weapon": "Sharp Fangs"
    },
    "Bear": {
        "name": "Bear",
        "health": 80,
        "weapon": "Sharp Claws"
    }
}